delivery_optimizer/__init__.py
delivery_optimizer/optimizer.py
delivery_optimizer-1.0.0.dist-info/licenses/LICENSE
delivery_optimizer-1.0.0.dist-info/METADATA
delivery_optimizer-1.0.0.dist-info/WHEEL
delivery_optimizer-1.0.0.dist-info/top_level.txt
delivery_optimizer-1.0.0.dist-info/RECORD
