Metadata-Version: 2.4
Name: delivery-optimizer
Version: 1.0.0
Summary: A Python library for calculating delivery distances and pricing using the Haversine formula
Home-page: https://github.com/AbhishekSharmaIE/courier-delivery-system
Author: Abhishek Sharma
Author-email: abhishekmsharma21@gmail.com
Project-URL: Bug Reports, https://github.com/AbhishekSharmaIE/courier-delivery-system/issues
Project-URL: Source, https://github.com/AbhishekSharmaIE/courier-delivery-system
Project-URL: Documentation, https://github.com/AbhishekSharmaIE/courier-delivery-system#readme
Keywords: delivery,distance,haversine,pricing,courier,logistics,geolocation
Classifier: Development Status :: 4 - Beta
Classifier: Intended Audience :: Developers
Classifier: Topic :: Software Development :: Libraries :: Python Modules
Classifier: Topic :: Scientific/Engineering :: GIS
Classifier: License :: OSI Approved :: MIT License
Classifier: Programming Language :: Python :: 3
Classifier: Programming Language :: Python :: 3.8
Classifier: Programming Language :: Python :: 3.9
Classifier: Programming Language :: Python :: 3.10
Classifier: Programming Language :: Python :: 3.11
Classifier: Programming Language :: Python :: 3.12
Classifier: Operating System :: OS Independent
Requires-Python: >=3.8
License-File: LICENSE
Dynamic: author
Dynamic: author-email
Dynamic: classifier
Dynamic: description
Dynamic: description-content-type
Dynamic: home-page
Dynamic: keywords
Dynamic: license-file
Dynamic: project-url
Dynamic: requires-python
Dynamic: summary
